spok/__init__.py
spok/smath.py
spok/spok.py
spok/utils.py
spok/analysis/mva.py
spok/coordinates/__init__.py
spok/coordinates/coordinates.py
spok/data/__init__.py
spok/models/__init__.py
spok/models/planetary.py
spok/plot/__init__.py
spok/plot/planet_env.py
spok-0.1.1.dist-info/LICENSE
spok-0.1.1.dist-info/WHEEL
spok-0.1.1.dist-info/METADATA
spok-0.1.1.dist-info/RECORD
