Metadata-Version: 2.1
Name: spok
Version: 0.1.1
Summary: Space Plasmas Observations Kit
Keywords: spok,plasma-physics
Author-email: Nicolas Aunai <nicolas.aunai@lpp.polytechnique.fr>
Maintainer-email: Nicolas Aunai <nicolas.aunai@lpp.polytechnique.fr>
Requires-Python: >=3.8
Classifier: Development Status :: 2 - Pre-Alpha
Classifier: Intended Audience :: Science/Research
Classifier: Topic :: Scientific/Engineering :: Physics
Classifier: License :: OSI Approved :: GNU General Public License v3 (GPLv3)
Classifier: Natural Language :: English
Classifier: Programming Language :: Python :: 3
Classifier: Programming Language :: Python :: 3.8
Classifier: Programming Language :: Python :: 3.9
Classifier: Programming Language :: Python :: 3.10
Classifier: Programming Language :: Python :: 3.11
Classifier: Programming Language :: Python :: 3.12
Requires-Dist: pandas
Requires-Dist: numpy
Requires-Dist: matplotlib
Requires-Dist: scipy
Project-URL: homepage, https://github.com/LaboratoryOfPlasmaPhysics/spok
